{
  "name": "angular-microfrontend-boilerplate",
  "shared": [
    {
      "packageName": "@angular-architects/module-federation",
      "outFileName": "_angular_architects_module_federation.kRLeznz7g2-dev.js",
      "requiredVersion": "^20.0.0",
      "singleton": true,
      "strictVersion": true,
      "version": "20.0.0"
    },
    {
      "packageName": "@angular/animations",
      "outFileName": "_angular_animations.9bmMRpnKPa-dev.js",
      "requiredVersion": "^20.3.18",
      "singleton": true,
      "strictVersion": true,
      "version": "20.3.18"
    },
    {
      "packageName": "@angular/animations/browser",
      "outFileName": "_angular_animations_browser.p4Be9vK14O-dev.js",
      "requiredVersion": "^20.3.18",
      "singleton": true,
      "strictVersion": true,
      "version": "20.3.18"
    },
    {
      "packageName": "@angular/cdk",
      "outFileName": "_angular_cdk.tB8lD5X9WW-dev.js",
      "requiredVersion": "^20.2.14",
      "singleton": true,
      "strictVersion": true,
      "version": "20.2.14"
    },
    {
      "packageName": "@angular/cdk/a11y",
      "outFileName": "_angular_cdk_a11y.LQdmn9VVu1-dev.js",
      "requiredVersion": "^20.2.14",
      "singleton": true,
      "strictVersion": true,
      "version": "20.2.14"
    },
    {
      "packageName": "@angular/cdk/accordion",
      "outFileName": "_angular_cdk_accordion._pEtSV-etR-dev.js",
      "requiredVersion": "^20.2.14",
      "singleton": true,
      "strictVersion": true,
      "version": "20.2.14"
    },
    {
      "packageName": "@angular/cdk/bidi",
      "outFileName": "_angular_cdk_bidi.mWkN1X_bzc-dev.js",
      "requiredVersion": "^20.2.14",
      "singleton": true,
      "strictVersion": true,
      "version": "20.2.14"
    },
    {
      "packageName": "@angular/cdk/clipboard",
      "outFileName": "_angular_cdk_clipboard.4NnriUfngn-dev.js",
      "requiredVersion": "^20.2.14",
      "singleton": true,
      "strictVersion": true,
      "version": "20.2.14"
    },
    {
      "packageName": "@angular/cdk/coercion",
      "outFileName": "_angular_cdk_coercion.FW0ghakEto-dev.js",
      "requiredVersion": "^20.2.14",
      "singleton": true,
      "strictVersion": true,
      "version": "20.2.14"
    },
    {
      "packageName": "@angular/cdk/coercion/private",
      "outFileName": "_angular_cdk_coercion_private.vJAS8Udads-dev.js",
      "requiredVersion": "^20.2.14",
      "singleton": true,
      "strictVersion": true,
      "version": "20.2.14"
    },
    {
      "packageName": "@angular/cdk/collections",
      "outFileName": "_angular_cdk_collections.KPrzV4W0EQ-dev.js",
      "requiredVersion": "^20.2.14",
      "singleton": true,
      "strictVersion": true,
      "version": "20.2.14"
    },
    {
      "packageName": "@angular/cdk/dialog",
      "outFileName": "_angular_cdk_dialog.5lGxfN2N9O-dev.js",
      "requiredVersion": "^20.2.14",
      "singleton": true,
      "strictVersion": true,
      "version": "20.2.14"
    },
    {
      "packageName": "@angular/cdk/drag-drop",
      "outFileName": "_angular_cdk_drag_drop.HeudmRH0Fq-dev.js",
      "requiredVersion": "^20.2.14",
      "singleton": true,
      "strictVersion": true,
      "version": "20.2.14"
    },
    {
      "packageName": "@angular/cdk/keycodes",
      "outFileName": "_angular_cdk_keycodes.bj1QmxF6In-dev.js",
      "requiredVersion": "^20.2.14",
      "singleton": true,
      "strictVersion": true,
      "version": "20.2.14"
    },
    {
      "packageName": "@angular/cdk/layout",
      "outFileName": "_angular_cdk_layout.KBeKMiXtbV-dev.js",
      "requiredVersion": "^20.2.14",
      "singleton": true,
      "strictVersion": true,
      "version": "20.2.14"
    },
    {
      "packageName": "@angular/cdk/listbox",
      "outFileName": "_angular_cdk_listbox.w9vUt-r6iv-dev.js",
      "requiredVersion": "^20.2.14",
      "singleton": true,
      "strictVersion": true,
      "version": "20.2.14"
    },
    {
      "packageName": "@angular/cdk/menu",
      "outFileName": "_angular_cdk_menu.m6WkGBBi3S-dev.js",
      "requiredVersion": "^20.2.14",
      "singleton": true,
      "strictVersion": true,
      "version": "20.2.14"
    },
    {
      "packageName": "@angular/cdk/observers",
      "outFileName": "_angular_cdk_observers.nod5P2r-pP-dev.js",
      "requiredVersion": "^20.2.14",
      "singleton": true,
      "strictVersion": true,
      "version": "20.2.14"
    },
    {
      "packageName": "@angular/cdk/observers/private",
      "outFileName": "_angular_cdk_observers_private.hmkTrjm97o-dev.js",
      "requiredVersion": "^20.2.14",
      "singleton": true,
      "strictVersion": true,
      "version": "20.2.14"
    },
    {
      "packageName": "@angular/cdk/overlay",
      "outFileName": "_angular_cdk_overlay.8AFcjFkGCp-dev.js",
      "requiredVersion": "^20.2.14",
      "singleton": true,
      "strictVersion": true,
      "version": "20.2.14"
    },
    {
      "packageName": "@angular/cdk/platform",
      "outFileName": "_angular_cdk_platform.gmhAZIS8aY-dev.js",
      "requiredVersion": "^20.2.14",
      "singleton": true,
      "strictVersion": true,
      "version": "20.2.14"
    },
    {
      "packageName": "@angular/cdk/portal",
      "outFileName": "_angular_cdk_portal.HwwwRt5kQh-dev.js",
      "requiredVersion": "^20.2.14",
      "singleton": true,
      "strictVersion": true,
      "version": "20.2.14"
    },
    {
      "packageName": "@angular/cdk/private",
      "outFileName": "_angular_cdk_private.tgi2PGDkVr-dev.js",
      "requiredVersion": "^20.2.14",
      "singleton": true,
      "strictVersion": true,
      "version": "20.2.14"
    },
    {
      "packageName": "@angular/cdk/scrolling",
      "outFileName": "_angular_cdk_scrolling.UWSit7eyg--dev.js",
      "requiredVersion": "^20.2.14",
      "singleton": true,
      "strictVersion": true,
      "version": "20.2.14"
    },
    {
      "packageName": "@angular/cdk/stepper",
      "outFileName": "_angular_cdk_stepper.TYXpEEtcFA-dev.js",
      "requiredVersion": "^20.2.14",
      "singleton": true,
      "strictVersion": true,
      "version": "20.2.14"
    },
    {
      "packageName": "@angular/cdk/table",
      "outFileName": "_angular_cdk_table.LqBvoUZAyH-dev.js",
      "requiredVersion": "^20.2.14",
      "singleton": true,
      "strictVersion": true,
      "version": "20.2.14"
    },
    {
      "packageName": "@angular/cdk/text-field",
      "outFileName": "_angular_cdk_text_field.rTKMuT1p1W-dev.js",
      "requiredVersion": "^20.2.14",
      "singleton": true,
      "strictVersion": true,
      "version": "20.2.14"
    },
    {
      "packageName": "@angular/cdk/tree",
      "outFileName": "_angular_cdk_tree.mCcsOOdvrE-dev.js",
      "requiredVersion": "^20.2.14",
      "singleton": true,
      "strictVersion": true,
      "version": "20.2.14"
    },
    {
      "packageName": "@angular/common",
      "outFileName": "_angular_common.RUen-bNun9-dev.js",
      "requiredVersion": "^20.3.0",
      "singleton": true,
      "strictVersion": true,
      "version": "20.3.18"
    },
    {
      "packageName": "@angular/common/http",
      "outFileName": "_angular_common_http.I50WzkmoBS-dev.js",
      "requiredVersion": "^20.3.0",
      "singleton": true,
      "strictVersion": true,
      "version": "20.3.18"
    },
    {
      "packageName": "@angular/compiler",
      "outFileName": "_angular_compiler.sUJu0fZ0xF-dev.js",
      "requiredVersion": "^20.3.0",
      "singleton": true,
      "strictVersion": true,
      "version": "20.3.18"
    },
    {
      "packageName": "@angular/core",
      "outFileName": "_angular_core.UaJ-nJ20EH-dev.js",
      "requiredVersion": "^20.3.0",
      "singleton": true,
      "strictVersion": true,
      "version": "20.3.18"
    },
    {
      "packageName": "@angular/core/event-dispatch-contract.min.js",
      "outFileName": "_angular_core_event_dispatch_contract_min_js._vHDEl2mMz-dev.js",
      "requiredVersion": "^20.3.0",
      "singleton": true,
      "strictVersion": true,
      "version": "20.3.18"
    },
    {
      "packageName": "@angular/core/primitives/di",
      "outFileName": "_angular_core_primitives_di.WkatWHI0h0-dev.js",
      "requiredVersion": "^20.3.0",
      "singleton": true,
      "strictVersion": true,
      "version": "20.3.18"
    },
    {
      "packageName": "@angular/core/primitives/event-dispatch",
      "outFileName": "_angular_core_primitives_event_dispatch.GvRB5lLXR0-dev.js",
      "requiredVersion": "^20.3.0",
      "singleton": true,
      "strictVersion": true,
      "version": "20.3.18"
    },
    {
      "packageName": "@angular/core/primitives/signals",
      "outFileName": "_angular_core_primitives_signals.7GazpuW0Wm-dev.js",
      "requiredVersion": "^20.3.0",
      "singleton": true,
      "strictVersion": true,
      "version": "20.3.18"
    },
    {
      "packageName": "@angular/core/rxjs-interop",
      "outFileName": "_angular_core_rxjs_interop.Qya9UMLszi-dev.js",
      "requiredVersion": "^20.3.0",
      "singleton": true,
      "strictVersion": true,
      "version": "20.3.18"
    },
    {
      "packageName": "@angular/forms",
      "outFileName": "_angular_forms.2004JIf9gG-dev.js",
      "requiredVersion": "^20.3.0",
      "singleton": true,
      "strictVersion": true,
      "version": "20.3.18"
    },
    {
      "packageName": "@angular/material",
      "outFileName": "_angular_material.bpQIrqKtZu-dev.js",
      "requiredVersion": "^20.2.14",
      "singleton": true,
      "strictVersion": true,
      "version": "20.2.14"
    },
    {
      "packageName": "@angular/material/autocomplete",
      "outFileName": "_angular_material_autocomplete.9W1lmrhcXE-dev.js",
      "requiredVersion": "^20.2.14",
      "singleton": true,
      "strictVersion": true,
      "version": "20.2.14"
    },
    {
      "packageName": "@angular/material/badge",
      "outFileName": "_angular_material_badge.ncU8t0tD8I-dev.js",
      "requiredVersion": "^20.2.14",
      "singleton": true,
      "strictVersion": true,
      "version": "20.2.14"
    },
    {
      "packageName": "@angular/material/bottom-sheet",
      "outFileName": "_angular_material_bottom_sheet.u9u9bi34JQ-dev.js",
      "requiredVersion": "^20.2.14",
      "singleton": true,
      "strictVersion": true,
      "version": "20.2.14"
    },
    {
      "packageName": "@angular/material/button",
      "outFileName": "_angular_material_button.Af_7_iLy4v-dev.js",
      "requiredVersion": "^20.2.14",
      "singleton": true,
      "strictVersion": true,
      "version": "20.2.14"
    },
    {
      "packageName": "@angular/material/button-toggle",
      "outFileName": "_angular_material_button_toggle.tlTSSd8pQz-dev.js",
      "requiredVersion": "^20.2.14",
      "singleton": true,
      "strictVersion": true,
      "version": "20.2.14"
    },
    {
      "packageName": "@angular/material/card",
      "outFileName": "_angular_material_card.iCNkqw4OnZ-dev.js",
      "requiredVersion": "^20.2.14",
      "singleton": true,
      "strictVersion": true,
      "version": "20.2.14"
    },
    {
      "packageName": "@angular/material/checkbox",
      "outFileName": "_angular_material_checkbox.XSzXEqWF3D-dev.js",
      "requiredVersion": "^20.2.14",
      "singleton": true,
      "strictVersion": true,
      "version": "20.2.14"
    },
    {
      "packageName": "@angular/material/chips",
      "outFileName": "_angular_material_chips.r5MQnJTU-J-dev.js",
      "requiredVersion": "^20.2.14",
      "singleton": true,
      "strictVersion": true,
      "version": "20.2.14"
    },
    {
      "packageName": "@angular/material/core",
      "outFileName": "_angular_material_core.PKboEhZrYr-dev.js",
      "requiredVersion": "^20.2.14",
      "singleton": true,
      "strictVersion": true,
      "version": "20.2.14"
    },
    {
      "packageName": "@angular/material/datepicker",
      "outFileName": "_angular_material_datepicker.BC2ocmwiPF-dev.js",
      "requiredVersion": "^20.2.14",
      "singleton": true,
      "strictVersion": true,
      "version": "20.2.14"
    },
    {
      "packageName": "@angular/material/dialog",
      "outFileName": "_angular_material_dialog.gXy8ddrs_j-dev.js",
      "requiredVersion": "^20.2.14",
      "singleton": true,
      "strictVersion": true,
      "version": "20.2.14"
    },
    {
      "packageName": "@angular/material/divider",
      "outFileName": "_angular_material_divider.LpqHzQMU3n-dev.js",
      "requiredVersion": "^20.2.14",
      "singleton": true,
      "strictVersion": true,
      "version": "20.2.14"
    },
    {
      "packageName": "@angular/material/expansion",
      "outFileName": "_angular_material_expansion.L-n5P0kmQM-dev.js",
      "requiredVersion": "^20.2.14",
      "singleton": true,
      "strictVersion": true,
      "version": "20.2.14"
    },
    {
      "packageName": "@angular/material/form-field",
      "outFileName": "_angular_material_form_field.DHbfZN2CgT-dev.js",
      "requiredVersion": "^20.2.14",
      "singleton": true,
      "strictVersion": true,
      "version": "20.2.14"
    },
    {
      "packageName": "@angular/material/grid-list",
      "outFileName": "_angular_material_grid_list.7MK6a4dwj0-dev.js",
      "requiredVersion": "^20.2.14",
      "singleton": true,
      "strictVersion": true,
      "version": "20.2.14"
    },
    {
      "packageName": "@angular/material/icon",
      "outFileName": "_angular_material_icon.idJzLw9xCC-dev.js",
      "requiredVersion": "^20.2.14",
      "singleton": true,
      "strictVersion": true,
      "version": "20.2.14"
    },
    {
      "packageName": "@angular/material/input",
      "outFileName": "_angular_material_input.WzIvKmbP2T-dev.js",
      "requiredVersion": "^20.2.14",
      "singleton": true,
      "strictVersion": true,
      "version": "20.2.14"
    },
    {
      "packageName": "@angular/material/list",
      "outFileName": "_angular_material_list.0Bq6GXPdOF-dev.js",
      "requiredVersion": "^20.2.14",
      "singleton": true,
      "strictVersion": true,
      "version": "20.2.14"
    },
    {
      "packageName": "@angular/material/menu",
      "outFileName": "_angular_material_menu.g-OVhgpu3Y-dev.js",
      "requiredVersion": "^20.2.14",
      "singleton": true,
      "strictVersion": true,
      "version": "20.2.14"
    },
    {
      "packageName": "@angular/material/paginator",
      "outFileName": "_angular_material_paginator.FoVS052IaY-dev.js",
      "requiredVersion": "^20.2.14",
      "singleton": true,
      "strictVersion": true,
      "version": "20.2.14"
    },
    {
      "packageName": "@angular/material/progress-bar",
      "outFileName": "_angular_material_progress_bar.7trWQmKZJe-dev.js",
      "requiredVersion": "^20.2.14",
      "singleton": true,
      "strictVersion": true,
      "version": "20.2.14"
    },
    {
      "packageName": "@angular/material/progress-spinner",
      "outFileName": "_angular_material_progress_spinner._vT2k1cwd_-dev.js",
      "requiredVersion": "^20.2.14",
      "singleton": true,
      "strictVersion": true,
      "version": "20.2.14"
    },
    {
      "packageName": "@angular/material/radio",
      "outFileName": "_angular_material_radio.CIP0UBp-Xc-dev.js",
      "requiredVersion": "^20.2.14",
      "singleton": true,
      "strictVersion": true,
      "version": "20.2.14"
    },
    {
      "packageName": "@angular/material/select",
      "outFileName": "_angular_material_select.z7llG6j9gQ-dev.js",
      "requiredVersion": "^20.2.14",
      "singleton": true,
      "strictVersion": true,
      "version": "20.2.14"
    },
    {
      "packageName": "@angular/material/sidenav",
      "outFileName": "_angular_material_sidenav.rRyl16jKDI-dev.js",
      "requiredVersion": "^20.2.14",
      "singleton": true,
      "strictVersion": true,
      "version": "20.2.14"
    },
    {
      "packageName": "@angular/material/slide-toggle",
      "outFileName": "_angular_material_slide_toggle.DnM5RhJFVR-dev.js",
      "requiredVersion": "^20.2.14",
      "singleton": true,
      "strictVersion": true,
      "version": "20.2.14"
    },
    {
      "packageName": "@angular/material/slider",
      "outFileName": "_angular_material_slider.UgirDEEnEA-dev.js",
      "requiredVersion": "^20.2.14",
      "singleton": true,
      "strictVersion": true,
      "version": "20.2.14"
    },
    {
      "packageName": "@angular/material/snack-bar",
      "outFileName": "_angular_material_snack_bar.ffxZex8scL-dev.js",
      "requiredVersion": "^20.2.14",
      "singleton": true,
      "strictVersion": true,
      "version": "20.2.14"
    },
    {
      "packageName": "@angular/material/sort",
      "outFileName": "_angular_material_sort.LU_Xz1Xjqi-dev.js",
      "requiredVersion": "^20.2.14",
      "singleton": true,
      "strictVersion": true,
      "version": "20.2.14"
    },
    {
      "packageName": "@angular/material/stepper",
      "outFileName": "_angular_material_stepper.W_m5ksoDS2-dev.js",
      "requiredVersion": "^20.2.14",
      "singleton": true,
      "strictVersion": true,
      "version": "20.2.14"
    },
    {
      "packageName": "@angular/material/table",
      "outFileName": "_angular_material_table.uZLa2ljc-N-dev.js",
      "requiredVersion": "^20.2.14",
      "singleton": true,
      "strictVersion": true,
      "version": "20.2.14"
    },
    {
      "packageName": "@angular/material/tabs",
      "outFileName": "_angular_material_tabs.Gz4o3aYRXq-dev.js",
      "requiredVersion": "^20.2.14",
      "singleton": true,
      "strictVersion": true,
      "version": "20.2.14"
    },
    {
      "packageName": "@angular/material/timepicker",
      "outFileName": "_angular_material_timepicker.KBnpnBkBye-dev.js",
      "requiredVersion": "^20.2.14",
      "singleton": true,
      "strictVersion": true,
      "version": "20.2.14"
    },
    {
      "packageName": "@angular/material/toolbar",
      "outFileName": "_angular_material_toolbar.3Tfti9N6kF-dev.js",
      "requiredVersion": "^20.2.14",
      "singleton": true,
      "strictVersion": true,
      "version": "20.2.14"
    },
    {
      "packageName": "@angular/material/tooltip",
      "outFileName": "_angular_material_tooltip.yGLUlZrjRQ-dev.js",
      "requiredVersion": "^20.2.14",
      "singleton": true,
      "strictVersion": true,
      "version": "20.2.14"
    },
    {
      "packageName": "@angular/material/tree",
      "outFileName": "_angular_material_tree.LRmMxOK2Pk-dev.js",
      "requiredVersion": "^20.2.14",
      "singleton": true,
      "strictVersion": true,
      "version": "20.2.14"
    },
    {
      "packageName": "@angular/platform-browser",
      "outFileName": "_angular_platform_browser.A2qfS6b3b0-dev.js",
      "requiredVersion": "^20.3.0",
      "singleton": true,
      "strictVersion": true,
      "version": "20.3.18"
    },
    {
      "packageName": "@angular/platform-browser/animations",
      "outFileName": "_angular_platform_browser_animations.oVDvuo16wZ-dev.js",
      "requiredVersion": "^20.3.0",
      "singleton": true,
      "strictVersion": true,
      "version": "20.3.18"
    },
    {
      "packageName": "@angular/platform-browser/animations/async",
      "outFileName": "_angular_platform_browser_animations_async.ChknEiDW06-dev.js",
      "requiredVersion": "^20.3.0",
      "singleton": true,
      "strictVersion": true,
      "version": "20.3.18"
    },
    {
      "packageName": "@angular/router",
      "outFileName": "_angular_router.oeMgRUyTgL-dev.js",
      "requiredVersion": "^20.3.0",
      "singleton": true,
      "strictVersion": true,
      "version": "20.3.18"
    },
    {
      "packageName": "rxjs",
      "outFileName": "rxjs.aGz8wqmASK-dev.js",
      "requiredVersion": "~7.8.0",
      "singleton": true,
      "strictVersion": true,
      "version": "7.8.2"
    },
    {
      "packageName": "rxjs/operators",
      "outFileName": "rxjs_operators.H-Y36yd7sh-dev.js",
      "requiredVersion": "~7.8.0",
      "singleton": true,
      "strictVersion": true,
      "version": "7.8.2"
    },
    {
      "packageName": "tslib",
      "outFileName": "tslib.LNDoO8_Bu8-dev.js",
      "requiredVersion": "^2.3.0",
      "singleton": true,
      "strictVersion": true,
      "version": "2.8.1"
    },
    {
      "singleton": false,
      "strictVersion": false,
      "version": "0.0.0",
      "requiredVersion": "0.0.0",
      "packageName": "@nf-internal/chunk-WB3BDYO7",
      "outFileName": "chunk-WB3BDYO7.js"
    },
    {
      "singleton": false,
      "strictVersion": false,
      "version": "0.0.0",
      "requiredVersion": "0.0.0",
      "packageName": "@nf-internal/chunk-TH4QT4CD",
      "outFileName": "chunk-TH4QT4CD.js"
    },
    {
      "singleton": false,
      "strictVersion": false,
      "version": "0.0.0",
      "requiredVersion": "0.0.0",
      "packageName": "@nf-internal/chunk-IE2S7NZU",
      "outFileName": "chunk-IE2S7NZU.js"
    },
    {
      "singleton": false,
      "strictVersion": false,
      "version": "0.0.0",
      "requiredVersion": "0.0.0",
      "packageName": "@nf-internal/chunk-FDEFXAFZ",
      "outFileName": "chunk-FDEFXAFZ.js"
    },
    {
      "singleton": false,
      "strictVersion": false,
      "version": "0.0.0",
      "requiredVersion": "0.0.0",
      "packageName": "@nf-internal/chunk-HPIPHQYM",
      "outFileName": "chunk-HPIPHQYM.js"
    },
    {
      "singleton": false,
      "strictVersion": false,
      "version": "0.0.0",
      "requiredVersion": "0.0.0",
      "packageName": "@nf-internal/chunk-AZJ7ARY2",
      "outFileName": "chunk-AZJ7ARY2.js"
    },
    {
      "singleton": false,
      "strictVersion": false,
      "version": "0.0.0",
      "requiredVersion": "0.0.0",
      "packageName": "@nf-internal/chunk-T3PQMW22",
      "outFileName": "chunk-T3PQMW22.js"
    },
    {
      "singleton": false,
      "strictVersion": false,
      "version": "0.0.0",
      "requiredVersion": "0.0.0",
      "packageName": "@nf-internal/chunk-5FRKND7I",
      "outFileName": "chunk-5FRKND7I.js"
    },
    {
      "singleton": false,
      "strictVersion": false,
      "version": "0.0.0",
      "requiredVersion": "0.0.0",
      "packageName": "@nf-internal/chunk-MHQKYKZ7",
      "outFileName": "chunk-MHQKYKZ7.js"
    },
    {
      "singleton": false,
      "strictVersion": false,
      "version": "0.0.0",
      "requiredVersion": "0.0.0",
      "packageName": "@nf-internal/chunk-LUJNHF63",
      "outFileName": "chunk-LUJNHF63.js"
    },
    {
      "singleton": false,
      "strictVersion": false,
      "version": "0.0.0",
      "requiredVersion": "0.0.0",
      "packageName": "@nf-internal/chunk-ZFKBSYQK",
      "outFileName": "chunk-ZFKBSYQK.js"
    },
    {
      "singleton": false,
      "strictVersion": false,
      "version": "0.0.0",
      "requiredVersion": "0.0.0",
      "packageName": "@nf-internal/chunk-HPPTXTE6",
      "outFileName": "chunk-HPPTXTE6.js"
    },
    {
      "singleton": false,
      "strictVersion": false,
      "version": "0.0.0",
      "requiredVersion": "0.0.0",
      "packageName": "@nf-internal/chunk-N2OCNCWW",
      "outFileName": "chunk-N2OCNCWW.js"
    },
    {
      "singleton": false,
      "strictVersion": false,
      "version": "0.0.0",
      "requiredVersion": "0.0.0",
      "packageName": "@nf-internal/chunk-CNEYRSCE",
      "outFileName": "chunk-CNEYRSCE.js"
    },
    {
      "singleton": false,
      "strictVersion": false,
      "version": "0.0.0",
      "requiredVersion": "0.0.0",
      "packageName": "@nf-internal/chunk-ZPYOT6KO",
      "outFileName": "chunk-ZPYOT6KO.js"
    },
    {
      "singleton": false,
      "strictVersion": false,
      "version": "0.0.0",
      "requiredVersion": "0.0.0",
      "packageName": "@nf-internal/chunk-5OW5SHVI",
      "outFileName": "chunk-5OW5SHVI.js"
    },
    {
      "singleton": false,
      "strictVersion": false,
      "version": "0.0.0",
      "requiredVersion": "0.0.0",
      "packageName": "@nf-internal/chunk-HZ7A6S7I",
      "outFileName": "chunk-HZ7A6S7I.js"
    },
    {
      "singleton": false,
      "strictVersion": false,
      "version": "0.0.0",
      "requiredVersion": "0.0.0",
      "packageName": "@nf-internal/chunk-MLWVG7ND",
      "outFileName": "chunk-MLWVG7ND.js"
    },
    {
      "singleton": false,
      "strictVersion": false,
      "version": "0.0.0",
      "requiredVersion": "0.0.0",
      "packageName": "@nf-internal/chunk-WI4TWG3P",
      "outFileName": "chunk-WI4TWG3P.js"
    },
    {
      "singleton": false,
      "strictVersion": false,
      "version": "0.0.0",
      "requiredVersion": "0.0.0",
      "packageName": "@nf-internal/chunk-WEB3F25G",
      "outFileName": "chunk-WEB3F25G.js"
    },
    {
      "singleton": false,
      "strictVersion": false,
      "version": "0.0.0",
      "requiredVersion": "0.0.0",
      "packageName": "@nf-internal/chunk-C7GPBAE3",
      "outFileName": "chunk-C7GPBAE3.js"
    },
    {
      "singleton": false,
      "strictVersion": false,
      "version": "0.0.0",
      "requiredVersion": "0.0.0",
      "packageName": "@nf-internal/chunk-6H6NL4EL",
      "outFileName": "chunk-6H6NL4EL.js"
    },
    {
      "singleton": false,
      "strictVersion": false,
      "version": "0.0.0",
      "requiredVersion": "0.0.0",
      "packageName": "@nf-internal/chunk-ZSJ667YT",
      "outFileName": "chunk-ZSJ667YT.js"
    },
    {
      "singleton": false,
      "strictVersion": false,
      "version": "0.0.0",
      "requiredVersion": "0.0.0",
      "packageName": "@nf-internal/chunk-KBAQXJRU",
      "outFileName": "chunk-KBAQXJRU.js"
    },
    {
      "singleton": false,
      "strictVersion": false,
      "version": "0.0.0",
      "requiredVersion": "0.0.0",
      "packageName": "@nf-internal/chunk-K5W4M6FW",
      "outFileName": "chunk-K5W4M6FW.js"
    },
    {
      "singleton": false,
      "strictVersion": false,
      "version": "0.0.0",
      "requiredVersion": "0.0.0",
      "packageName": "@nf-internal/chunk-4U7R3AWV",
      "outFileName": "chunk-4U7R3AWV.js"
    },
    {
      "singleton": false,
      "strictVersion": false,
      "version": "0.0.0",
      "requiredVersion": "0.0.0",
      "packageName": "@nf-internal/chunk-XGLHJJWH",
      "outFileName": "chunk-XGLHJJWH.js"
    },
    {
      "singleton": false,
      "strictVersion": false,
      "version": "0.0.0",
      "requiredVersion": "0.0.0",
      "packageName": "@nf-internal/chunk-WEGFPNI6",
      "outFileName": "chunk-WEGFPNI6.js"
    },
    {
      "singleton": false,
      "strictVersion": false,
      "version": "0.0.0",
      "requiredVersion": "0.0.0",
      "packageName": "@nf-internal/chunk-FNC7QTFY",
      "outFileName": "chunk-FNC7QTFY.js"
    },
    {
      "singleton": false,
      "strictVersion": false,
      "version": "0.0.0",
      "requiredVersion": "0.0.0",
      "packageName": "@nf-internal/chunk-4ZQVFAGS",
      "outFileName": "chunk-4ZQVFAGS.js"
    },
    {
      "singleton": false,
      "strictVersion": false,
      "version": "0.0.0",
      "requiredVersion": "0.0.0",
      "packageName": "@nf-internal/chunk-DJVGGCNM",
      "outFileName": "chunk-DJVGGCNM.js"
    },
    {
      "singleton": false,
      "strictVersion": false,
      "version": "0.0.0",
      "requiredVersion": "0.0.0",
      "packageName": "@nf-internal/chunk-JWJY4EQI",
      "outFileName": "chunk-JWJY4EQI.js"
    },
    {
      "singleton": false,
      "strictVersion": false,
      "version": "0.0.0",
      "requiredVersion": "0.0.0",
      "packageName": "@nf-internal/chunk-3DFIABJL",
      "outFileName": "chunk-3DFIABJL.js"
    },
    {
      "singleton": false,
      "strictVersion": false,
      "version": "0.0.0",
      "requiredVersion": "0.0.0",
      "packageName": "@nf-internal/chunk-KQI5WFMG",
      "outFileName": "chunk-KQI5WFMG.js"
    },
    {
      "singleton": false,
      "strictVersion": false,
      "version": "0.0.0",
      "requiredVersion": "0.0.0",
      "packageName": "@nf-internal/chunk-47WVURNA",
      "outFileName": "chunk-47WVURNA.js"
    },
    {
      "singleton": false,
      "strictVersion": false,
      "version": "0.0.0",
      "requiredVersion": "0.0.0",
      "packageName": "@nf-internal/chunk-KN5HOZMH",
      "outFileName": "chunk-KN5HOZMH.js"
    },
    {
      "singleton": false,
      "strictVersion": false,
      "version": "0.0.0",
      "requiredVersion": "0.0.0",
      "packageName": "@nf-internal/chunk-SWBBLCJO",
      "outFileName": "chunk-SWBBLCJO.js"
    },
    {
      "singleton": false,
      "strictVersion": false,
      "version": "0.0.0",
      "requiredVersion": "0.0.0",
      "packageName": "@nf-internal/chunk-RNYUCYEO",
      "outFileName": "chunk-RNYUCYEO.js"
    },
    {
      "singleton": false,
      "strictVersion": false,
      "version": "0.0.0",
      "requiredVersion": "0.0.0",
      "packageName": "@nf-internal/chunk-RLOP7IVB",
      "outFileName": "chunk-RLOP7IVB.js"
    },
    {
      "singleton": false,
      "strictVersion": false,
      "version": "0.0.0",
      "requiredVersion": "0.0.0",
      "packageName": "@nf-internal/chunk-LLIBQE7U",
      "outFileName": "chunk-LLIBQE7U.js"
    },
    {
      "singleton": false,
      "strictVersion": false,
      "version": "0.0.0",
      "requiredVersion": "0.0.0",
      "packageName": "@nf-internal/chunk-PSY7FISX",
      "outFileName": "chunk-PSY7FISX.js"
    },
    {
      "singleton": false,
      "strictVersion": false,
      "version": "0.0.0",
      "requiredVersion": "0.0.0",
      "packageName": "@nf-internal/chunk-FE42P4QJ",
      "outFileName": "chunk-FE42P4QJ.js"
    },
    {
      "singleton": false,
      "strictVersion": false,
      "version": "0.0.0",
      "requiredVersion": "0.0.0",
      "packageName": "@nf-internal/chunk-5MYPNHIQ",
      "outFileName": "chunk-5MYPNHIQ.js"
    },
    {
      "singleton": false,
      "strictVersion": false,
      "version": "0.0.0",
      "requiredVersion": "0.0.0",
      "packageName": "@nf-internal/chunk-G2EEYTQC",
      "outFileName": "chunk-G2EEYTQC.js"
    },
    {
      "singleton": false,
      "strictVersion": false,
      "version": "0.0.0",
      "requiredVersion": "0.0.0",
      "packageName": "@nf-internal/chunk-376HJEB2",
      "outFileName": "chunk-376HJEB2.js"
    },
    {
      "singleton": false,
      "strictVersion": false,
      "version": "0.0.0",
      "requiredVersion": "0.0.0",
      "packageName": "@nf-internal/chunk-TRAE3QXN",
      "outFileName": "chunk-TRAE3QXN.js"
    },
    {
      "singleton": false,
      "strictVersion": false,
      "version": "0.0.0",
      "requiredVersion": "0.0.0",
      "packageName": "@nf-internal/chunk-PAGWHQED",
      "outFileName": "chunk-PAGWHQED.js"
    },
    {
      "singleton": false,
      "strictVersion": false,
      "version": "0.0.0",
      "requiredVersion": "0.0.0",
      "packageName": "@nf-internal/chunk-NRUOOIWH",
      "outFileName": "chunk-NRUOOIWH.js"
    },
    {
      "singleton": false,
      "strictVersion": false,
      "version": "0.0.0",
      "requiredVersion": "0.0.0",
      "packageName": "@nf-internal/chunk-53QNMHMN",
      "outFileName": "chunk-53QNMHMN.js"
    },
    {
      "singleton": false,
      "strictVersion": false,
      "version": "0.0.0",
      "requiredVersion": "0.0.0",
      "packageName": "@nf-internal/chunk-7OK4ZKLA",
      "outFileName": "chunk-7OK4ZKLA.js"
    },
    {
      "singleton": false,
      "strictVersion": false,
      "version": "0.0.0",
      "requiredVersion": "0.0.0",
      "packageName": "@nf-internal/chunk-V2HTFPYN",
      "outFileName": "chunk-V2HTFPYN.js"
    },
    {
      "singleton": false,
      "strictVersion": false,
      "version": "0.0.0",
      "requiredVersion": "0.0.0",
      "packageName": "@nf-internal/chunk-PXBFTVYB",
      "outFileName": "chunk-PXBFTVYB.js"
    },
    {
      "singleton": false,
      "strictVersion": false,
      "version": "0.0.0",
      "requiredVersion": "0.0.0",
      "packageName": "@nf-internal/chunk-MRIWI62B",
      "outFileName": "chunk-MRIWI62B.js"
    },
    {
      "singleton": false,
      "strictVersion": false,
      "version": "0.0.0",
      "requiredVersion": "0.0.0",
      "packageName": "@nf-internal/chunk-WAL5Y5RR",
      "outFileName": "chunk-WAL5Y5RR.js"
    },
    {
      "singleton": false,
      "strictVersion": false,
      "version": "0.0.0",
      "requiredVersion": "0.0.0",
      "packageName": "@nf-internal/chunk-CW4NLAXQ",
      "outFileName": "chunk-CW4NLAXQ.js"
    },
    {
      "singleton": false,
      "strictVersion": false,
      "version": "0.0.0",
      "requiredVersion": "0.0.0",
      "packageName": "@nf-internal/chunk-ZYGAQD4B",
      "outFileName": "chunk-ZYGAQD4B.js"
    },
    {
      "singleton": false,
      "strictVersion": false,
      "version": "0.0.0",
      "requiredVersion": "0.0.0",
      "packageName": "@nf-internal/chunk-ADVBEMXY",
      "outFileName": "chunk-ADVBEMXY.js"
    },
    {
      "singleton": false,
      "strictVersion": false,
      "version": "0.0.0",
      "requiredVersion": "0.0.0",
      "packageName": "@nf-internal/chunk-IDUT7LWG",
      "outFileName": "chunk-IDUT7LWG.js"
    },
    {
      "singleton": false,
      "strictVersion": false,
      "version": "0.0.0",
      "requiredVersion": "0.0.0",
      "packageName": "@nf-internal/chunk-GWSCQGIY",
      "outFileName": "chunk-GWSCQGIY.js"
    },
    {
      "singleton": false,
      "strictVersion": false,
      "version": "0.0.0",
      "requiredVersion": "0.0.0",
      "packageName": "@nf-internal/chunk-TNJMLD77",
      "outFileName": "chunk-TNJMLD77.js"
    },
    {
      "singleton": false,
      "strictVersion": false,
      "version": "0.0.0",
      "requiredVersion": "0.0.0",
      "packageName": "@nf-internal/chunk-ULJYXHYS",
      "outFileName": "chunk-ULJYXHYS.js"
    },
    {
      "singleton": false,
      "strictVersion": false,
      "version": "0.0.0",
      "requiredVersion": "0.0.0",
      "packageName": "@nf-internal/chunk-CLGTVECU",
      "outFileName": "chunk-CLGTVECU.js"
    },
    {
      "singleton": false,
      "strictVersion": false,
      "version": "0.0.0",
      "requiredVersion": "0.0.0",
      "packageName": "@nf-internal/chunk-KSPW4LU3",
      "outFileName": "chunk-KSPW4LU3.js"
    },
    {
      "singleton": false,
      "strictVersion": false,
      "version": "0.0.0",
      "requiredVersion": "0.0.0",
      "packageName": "@nf-internal/chunk-WYINW7RH",
      "outFileName": "chunk-WYINW7RH.js"
    },
    {
      "singleton": false,
      "strictVersion": false,
      "version": "0.0.0",
      "requiredVersion": "0.0.0",
      "packageName": "@nf-internal/chunk-4ECZME2J",
      "outFileName": "chunk-4ECZME2J.js"
    },
    {
      "singleton": false,
      "strictVersion": false,
      "version": "0.0.0",
      "requiredVersion": "0.0.0",
      "packageName": "@nf-internal/chunk-T6G3UKWE",
      "outFileName": "chunk-T6G3UKWE.js"
    },
    {
      "singleton": false,
      "strictVersion": false,
      "version": "0.0.0",
      "requiredVersion": "0.0.0",
      "packageName": "@nf-internal/chunk-URG5APGO",
      "outFileName": "chunk-URG5APGO.js"
    },
    {
      "singleton": false,
      "strictVersion": false,
      "version": "0.0.0",
      "requiredVersion": "0.0.0",
      "packageName": "@nf-internal/chunk-SK4UPIA3",
      "outFileName": "chunk-SK4UPIA3.js"
    },
    {
      "singleton": false,
      "strictVersion": false,
      "version": "0.0.0",
      "requiredVersion": "0.0.0",
      "packageName": "@nf-internal/chunk-SK4UB4LE",
      "outFileName": "chunk-SK4UB4LE.js"
    },
    {
      "singleton": false,
      "strictVersion": false,
      "version": "0.0.0",
      "requiredVersion": "0.0.0",
      "packageName": "@nf-internal/chunk-WXPTAMPH",
      "outFileName": "chunk-WXPTAMPH.js"
    },
    {
      "packageName": "@angular/platform-server",
      "outFileName": "_angular_platform_server.qf0Qmshf-4-dev.js",
      "requiredVersion": "^20.3.0",
      "singleton": true,
      "strictVersion": true,
      "version": "20.3.18"
    },
    {
      "packageName": "@angular/platform-server/init",
      "outFileName": "_angular_platform_server_init.36VzKD5fp_-dev.js",
      "requiredVersion": "^20.3.0",
      "singleton": true,
      "strictVersion": true,
      "version": "20.3.18"
    },
    {
      "packageName": "@angular/ssr",
      "outFileName": "_angular_ssr.gLmISvZxDv-dev.js",
      "requiredVersion": "^20.3.20",
      "singleton": true,
      "strictVersion": true,
      "version": "20.3.20"
    },
    {
      "packageName": "@angular/ssr/node",
      "outFileName": "_angular_ssr_node.noeFgOdGzf-dev.js",
      "requiredVersion": "^20.3.20",
      "singleton": true,
      "strictVersion": true,
      "version": "20.3.20"
    },
    {
      "singleton": false,
      "strictVersion": false,
      "version": "0.0.0",
      "requiredVersion": "0.0.0",
      "packageName": "@nf-internal/chunk-KLBD2CNF",
      "outFileName": "chunk-KLBD2CNF.js"
    },
    {
      "singleton": false,
      "strictVersion": false,
      "version": "0.0.0",
      "requiredVersion": "0.0.0",
      "packageName": "@nf-internal/xhr2-6R4TS5IX",
      "outFileName": "xhr2-6R4TS5IX.js"
    },
    {
      "singleton": false,
      "strictVersion": false,
      "version": "0.0.0",
      "requiredVersion": "0.0.0",
      "packageName": "@nf-internal/chunk-3QVZCVE3",
      "outFileName": "chunk-3QVZCVE3.js"
    }
  ],
  "exposes": [
    {
      "key": "./Component",
      "outFileName": "Component.js",
      "dev": {
        "entryPoint": "/Users/arkomandal/Projects/Technology/ng-mf/src/app/app.ts"
      }
    }
  ],
  "buildNotificationsEndpoint": "/@angular-architects/native-federation:build-notifications"
}